nodcast/__init__.py
nodcast/article.py
nodcast/colors.py
nodcast/inst.py
nodcast/nodcast.py
nodcast/pdfsum.py
nodcast/startup.py
nodcast/tbox.py
nodcast/docs/log_file.log
nodcast/docs/new.yaml
nodcast/docs/examples/intro.yaml
nodcast/docs/examples/log_file.log
nodcast/docs/examples/Files/README.nct
nodcast/docs/examples/Files/log_file.log
nodcast/docs/examples/Files/sample_1.nct
nodcast/docs/examples/Files/sample_2.nct
nodcast/util/__init__.py
nodcast/util/colors.py
nodcast/util/common.py
nodcast/util/nlp_utils.py
nodcast/util/obj_util.py
nodcast/util/util.py
nodcast-0.1.19.dist-info/licenses/LICENSE
nodcast-0.1.19.dist-info/METADATA
nodcast-0.1.19.dist-info/WHEEL
nodcast-0.1.19.dist-info/entry_points.txt
nodcast-0.1.19.dist-info/top_level.txt
nodcast-0.1.19.dist-info/RECORD
