Metadata-Version: 2.4
Name: nodcast
Version: 0.1.19
Summary: NodCast, a text-based article reader and manager
Author-email: A Pouramini <pouramini@gmail.com>
License-Expression: MIT
Project-URL: Homepage, https://puraminy.github.io/nodcast/
Project-URL: Repository, https://github.com/puraminy/nodcast
Project-URL: Issues, https://github.com/puraminy/nodcast/issues
Keywords: text,reader,cli,article,tts
Requires-Python: >=3.6
License-File: LICENSE
Requires-Dist: requests
Requires-Dist: appdirs
Requires-Dist: PyYAML
Requires-Dist: gtts
Requires-Dist: python-vlc
Requires-Dist: importlib_resources
Provides-Extra: windows
Requires-Dist: windows-curses; extra == "windows"
Dynamic: license-file
